{
  "type": "forge:conditional",
  "recipes": [
    {
      "conditions": [
        {
          "type": "ornamental:config",
          "config": "showCopperBlocks"
        }
      ],
      "recipe": {
        "type": "minecraft:crafting_shaped",
        "key": {
          "#": {
            "item": "minecraft:oxidized_copper"
          }
        },
        "pattern": [
          "###"
        ],
        "result": {
          "count": 6,
          "item": "ornamental:oxidized_copper_slab"
        }
      }
    }
  ]
}