{
  "type": "forge:conditional",
  "recipes": [
    {
      "conditions": [
        {
          "config": "showPackedIceBlocks",
          "type": "ornamental:config"
        }
      ],
      "recipe": {
        "type": "minecraft:crafting_shaped",
        "pattern": [
          "#  ",
          "## ",
          "###"
        ],
        "key": {
          "#": {
            "item": "minecraft:packed_ice"
          }
        },
        "result": {
          "item": "ornamental:packed_ice_stairs",
          "count": 8
        }
      }
    }
  ]
}