{
  "type": "forge:conditional",
  "recipes": [
    {
      "conditions": [
        {
          "type": "ornamental:config",
          "config": "showQuartzBlocks"
        }
      ],
      "recipe": {
        "type": "minecraft:crafting_shaped",
        "key": {
          "#": {
            "item": "minecraft:quartz_block"
          },
          "/": {
            "item": "minecraft:quartz"
          }
        },
        "pattern": [
          "#/#",
          "#/#"
        ],
        "result": {
          "count": 3,
          "item": "ornamental:quartz_fence"
        }
      }
    }
  ]
}