{
  "render_type": "minecraft:cutout_mipped",
  "ambientocclusion": false,
  "textures": {
    "particle": "block/dirt",
    "bottom": "block/grass_block_top",
    "top": "block/grass_block_side",
    "overlay": "block/grass_block_side_overlay"
  },
  "elements": [{
    "from": [ 0, 0, 0 ],
    "to": [ 3, 16, 16 ],
    "faces": {
      "up":    { "uv": [  0,  3, 16,  0 ], "texture": "#bottom", "cullface": "up", "tintindex": 0 },
      "north": { "uv": [  0,  0,  3, 16 ], "texture": "#top", "cullface": "north" },
      "south": { "uv": [  0,  0,  3, 16 ], "texture": "#top", "cullface": "south" },
      "west":  { "uv": [ 16,  0,  0, 16 ], "texture": "#top", "cullface": "west" },
      "east":  { "uv": [  0,  0, 16, 16 ], "texture": "#top" }
    }
  }, {
    "from": [ 0, 0, 0 ],
    "to": [ 3, 16, 16 ],
    "faces": {
      "north": { "uv": [  0,  0,  3, 16 ], "texture": "#overlay", "cullface": "north", "tintindex": 0 },
      "south": { "uv": [  0,  0,  3, 16 ], "texture": "#overlay", "cullface": "south", "tintindex": 0 },
      "west":  { "uv": [ 16,  0,  0, 16 ], "texture": "#overlay", "cullface": "west", "tintindex": 0 },
      "east":  { "uv": [  0,  0, 16, 16 ], "texture": "#overlay", "tintindex": 0 }
    }
  }]
}
